onix/__init__.py
onix/book/__init__.py
onix/book/v2_1/__init__.py
onix/book/v2_1/reference/__init__.py
onix/book/v2_1/reference/book_2_1_reference.py
onix/book/v2_1/reference/onix_book_product_code_lists.py
onix/book/v2_1/reference/onix_xhtml_subset.py
onix/book/v2_1/short/__init__.py
onix/book/v2_1/short/book_2_1_short.py
onix/book/v2_1/short/onix_book_product_code_lists.py
onix/book/v2_1/short/onix_xhtml_subset.py
onix/book/v3_0/__init__.py
onix/book/v3_0/reference/__init__.py
onix/book/v3_0/reference/book_3_0_reference.py
onix/book/v3_0/reference/onix_book_product_code_lists.py
onix/book/v3_0/reference/onix_xhtml_subset.py
onix/book/v3_0/reference/strict/__init__.py
onix/book/v3_0/reference/strict/book_3_0_reference_strict.py
onix/book/v3_0/reference/strict/onix_book_product_code_lists.py
onix/book/v3_0/reference/strict/onix_xhtml_subset.py
onix/book/v3_0/short/__init__.py
onix/book/v3_0/short/book_3_0_short.py
onix/book/v3_0/short/onix_book_product_3_0_short.py
onix/book/v3_0/short/onix_book_product_code_lists.py
onix/book/v3_0/short/onix_xhtml_subset.py
onix/book/v3_0/short/strict/__init__.py
onix/book/v3_0/short/strict/book_3_0_short_strict.py
onix/book/v3_0/short/strict/onix_book_product_code_lists.py
onix/book/v3_0/short/strict/onix_xhtml_subset.py
onix/book/v3_1/__init__.py
onix/book/v3_1/reference/__init__.py
onix/book/v3_1/reference/onix_book_product_3_1_reference.py
onix/book/v3_1/reference/onix_book_product_code_lists.py
onix/book/v3_1/reference/onix_xhtml_subset.py
onix/book/v3_1/reference/strict/__init__.py
onix/book/v3_1/reference/strict/onix_book_product_3_1_reference_strict.py
onix/book/v3_1/reference/strict/onix_book_product_code_lists.py
onix/book/v3_1/reference/strict/onix_xhtml_subset.py
onix/book/v3_1/short/__init__.py
onix/book/v3_1/short/onix_book_product_3_1_short.py
onix/book/v3_1/short/onix_book_product_code_lists.py
onix/book/v3_1/short/onix_xhtml_subset.py
onix/book/v3_1/short/strict/__init__.py
python_onix-0.0.3.dist-info/LICENSE
python_onix-0.0.3.dist-info/METADATA
python_onix-0.0.3.dist-info/WHEEL
python_onix-0.0.3.dist-info/RECORD
