Metadata-Version: 2.1
Name: python-onix
Version: 0.0.3
Summary: Dataclasses for EDItEUR's ONIX standards
Author: Ömer Boratav
Author-email: omerboratav@gmail.com
Requires-Python: >=3.10,<4.0
Classifier: Programming Language :: Python :: 3
Classifier: Programming Language :: Python :: 3.10
Classifier: Programming Language :: Python :: 3.11
Classifier: Programming Language :: Python :: 3.12
Requires-Dist: furo (>=2024.5.6,<2025.0.0)
Requires-Dist: sphinx (>=7.3.7,<8.0.0)
Requires-Dist: xsdata[cli,lxml,soap] (>=24.5,<25.0)
